python_to_latex/__init__.py
python_to_latex/python_to_latex.py
python_to_latex-0.0.3.dist-info/LICENSE
python_to_latex-0.0.3.dist-info/METADATA
python_to_latex-0.0.3.dist-info/WHEEL
python_to_latex-0.0.3.dist-info/top_level.txt
python_to_latex-0.0.3.dist-info/RECORD
