Metadata-Version: 2.1
Name: python-to-latex
Version: 0.0.3
Summary: Python module to facilitate input in LaTex from Python scripts
Home-page: https://github.com/scythja123/TODO
Author: Sonja Stuedli
Author-email: scythja@gmail.com
License: GPLv3
Platform: any
Requires-Python: >=3
